waldur_slurm/__init__.py
waldur_slurm/common_utils.py
waldur_slurm/main.py
waldur_slurm/slurm_client/__init__.py
waldur_slurm/slurm_client/backend.py
waldur_slurm/slurm_client/base.py
waldur_slurm/slurm_client/client.py
waldur_slurm/slurm_client/exceptions.py
waldur_slurm/slurm_client/parser.py
waldur_slurm/slurm_client/structures.py
waldur_slurm/slurm_client/utils.py
waldur_slurm/slurm_waldur_utils.py
waldur_slurm/waldur_slurm_utils.py
waldur_slurm_agent-0.2.2.dist-info/LICENCE
waldur_slurm_agent-0.2.2.dist-info/METADATA
waldur_slurm_agent-0.2.2.dist-info/WHEEL
waldur_slurm_agent-0.2.2.dist-info/entry_points.txt
waldur_slurm_agent-0.2.2.dist-info/RECORD
