Metadata-Version: 2.1
Name: waldur-slurm-agent
Version: 0.2.2
Summary: SLURM integration module for Waldur.
Home-page: https://waldur.com
License: MIT
Author: OpenNode Team
Author-email: info@opennodecloud.com
Requires-Python: >=3.9,<4.0
Classifier: Intended Audience :: Developers
Classifier: License :: OSI Approved :: MIT License
Classifier: Operating System :: OS Independent
Classifier: Programming Language :: Python :: 3
Classifier: Programming Language :: Python :: 3.9
Classifier: Programming Language :: Python :: 3.10
Classifier: Programming Language :: Python :: 3.11
Classifier: Programming Language :: Python :: 3.12
Requires-Dist: python-waldur-client (==0.2.10)
Requires-Dist: pyyaml (==6.0.1)
Requires-Dist: requests (==2.27.1)
Requires-Dist: sentry-sdk (==1.14.0)
Project-URL: Documentation, https://docs.waldur.com
